examples/oro4.v

module top;

reg  [31:0] clk_d;
wire [31:0] clk;
reg  [31:0] oro_d;
wire [31:0] oro;
wire [0:0] andres;
reg  [31:0] res;

integer i;

assign clk = clk_d;
assign oro = oro_d;

and (andres, clk[0], oro[0]);

initial
  for (i = 0; i < 10; i = i + 1)
    begin
      #5 clk_d = 1;
      #5 clk_d = 0;
      #5 clk_d = 1;
      #5 clk_d = 0;
    end

always @(andres)
  begin
    $display("VERILOG %t SAW ANDRES CHANGE: %d\n", $time, andres);
  end

always @(clk)
  begin
    $display("VERILOG %t SAW CLK CHANGE: %d\n", $time, clk);
  end

always @(oro)
  begin
    $display("VERILOG %t SAW ORO CHANGE: %d\n", $time, oro);
  end    


initial

  begin
    clk_d = 0;
    oro_d = 0;

    $display("VERILOG DISPLAY AT TIME 0\n");
    $dumpvars;

    res = $apvm("oro", "oroboro", "oroboro");
    $display("VERILOG %t APVM returns!\n", $time);

  end

endmodule

examples/dump.vcd
$date
	Thu Dec 10 11:43:39 2015
$end
$version
	Icarus Verilog
$end
$timescale
	1s
$end
$scope module top $end
$var wire 1 ! andres $end
$var wire 32 " clk [31:0] $end
$var wire 32 # oro [31:0] $end
$var reg 32 $ clk_d [31:0] $end
$var integer 32 % i [31:0] $end
$var reg 32 & oro_d [31:0] $end
$var reg 32 ' res [31:0] $end
$upscope $end
$enddefinitions $end
#0
$dumpvars
b0 '
b0 &
b0 %
b0 $
b0 #
b0 "
0!
$end
#5
b1 $
b1 "
#10
b0 $
b0 "
#15
b1 $
b1 "
#20
b1 %
b0 $
b0 "
#25
b1 $
b1 "
#30
b0 $
b0 "
#31
b1 &
b1 #
#35
1!
b1 $
b1 "
#40
0!
b10 %
b0 $
b0 "
#45
1!
b1 $
b1 "
#46
0!
b10 &
b10 #
#50
b0 $
b0 "
#55
b1 $
b1 "
#60
b11 &
b11 #
b11 %
b0 $
b0 "
#65
1!
b1 $
b1 "
#70
0!
b0 $
b0 "
#75
1!
b1 $
b1 "
#76
0!
b100 &
b100 #
#80
b100 %
b0 $
b0 "
#85
b1 $
b1 "
#90
b0 $
b0 "
#91
b101 &
b101 #
#95
1!
b1 $
b1 "
#100
0!
b101 %
b0 $
b0 "
#105
1!
b1 $
b1 "
#106
0!
b110 &
b110 #
#110
b0 $
b0 "
#115
b1 $
b1 "
#120
b111 &
b111 #
b110 %
b0 $
b0 "
#125
1!
b1 $
b1 "
#130
0!
b0 $
b0 "
#135
1!
b1 $
b1 "
#136
0!
b1000 &
b1000 #
#140
b111 %
b0 $
b0 "
#145
b1 $
b1 "
#150
b0 $
b0 "
#151
b1001 &
b1001 #
#155
1!
b1 $
b1 "
#160
0!
b1000 %
b0 $
b0 "
#165
1!
b1 $
b1 "
#170
0!
b0 $
b0 "
#175
1!
b1 $
b1 "
#180
0!
b1001 %
b0 $
b0 "
#185
1!
b1 $
b1 "
#190
0!
b0 $
b0 "
#195
1!
b1 $
b1 "
#200
0!
b1010 %
b0 $
b0 "
